.gitignore
LICENSE
LICENSE_RUS
MANIFEST.in
README.md
requirements.txt
setup.cfg
setup.py
sberpm/__init__.py
sberpm/_holder.py
sberpm/_utils.py
sberpm/_version.py
sberpm.egg-info/PKG-INFO
sberpm.egg-info/SOURCES.txt
sberpm.egg-info/dependency_links.txt
sberpm.egg-info/requires.txt
sberpm.egg-info/top_level.txt
sberpm/autoinsights/__init__.py
sberpm/autoinsights/_influencing_activities.py
sberpm/autoinsights/file_obf/_influencing_activities.obfsbpm
sberpm/bpmn/__init__.py
sberpm/bpmn/_bpmn_file_to_graph.py
sberpm/bpmn/_bpmn_graph_to_file/__init__.py
sberpm/bpmn/_bpmn_graph_to_file/_bpmn_exporter.py
sberpm/bpmn/_bpmn_graph_to_file/_bpmn_xml_maker.py
sberpm/bpmn/_bpmn_graph_to_file/_petri_net_to_bpmn.py
sberpm/bpmn/_bpmn_graph_to_file/grandalf.py
sberpm/bpmn/_bpmn_graph_to_file/graphviz.py
sberpm/column_matching/__init__.py
sberpm/column_matching/_column_matching.py
sberpm/column_matching/file_obf/_column_matching_.obfsbpm
sberpm/conformance_checking/__init__.py
sberpm/conformance_checking/_conformance_checking.py
sberpm/conformance_checking/_token_replay.py
sberpm/decision_mining/__init__.py
sberpm/decision_mining/_decision_mining.py
sberpm/graph_stats/__init__.py
sberpm/graph_stats/centrality.py
sberpm/imitation/__init__.py
sberpm/imitation/_simulation.py
sberpm/imitation/_validation.py
sberpm/imitation/file_obf/_simulation.obfsbpm
sberpm/imitation/file_obf/_validation.obfsbpm
sberpm/metrics/__init__.py
sberpm/metrics/_activity_metric.py
sberpm/metrics/_base_metric.py
sberpm/metrics/_id_metric.py
sberpm/metrics/_trace_metric.py
sberpm/metrics/_transition_metric.py
sberpm/metrics/_user_metric.py
sberpm/metrics/_utils.py
sberpm/miners/__init__.py
sberpm/miners/_abstract_miner.py
sberpm/miners/_alpha_miner.py
sberpm/miners/_alpha_plus_miner.py
sberpm/miners/_auto_miner.py
sberpm/miners/_causal_miner.py
sberpm/miners/_correlation_miner.py
sberpm/miners/_heu_miner.py
sberpm/miners/_inductive_miner.py
sberpm/miners/_inductive_utils.py
sberpm/miners/_ml_miner.py
sberpm/miners/_parallel_miner.py
sberpm/miners/_simple_miner.py
sberpm/miners/file_obf/_auto_miner.obfsbpm
sberpm/miners/file_obf/_ml_miner.obfsbpm
