Metadata-Version: 2.1
Name: sberpm
Version: 2.5.1
Summary: Library that is intended to operate with various process mining tasks.
Author: Sberbank Process Mining Team
Author-email: AABugaenko@sberbank.ru
Classifier: Programming Language :: Python
Classifier: Intended Audience :: Developers
Classifier: Programming Language :: Python :: 3 :: Only
Classifier: Programming Language :: Python :: 3.7
Classifier: Programming Language :: Python :: 3.8
Classifier: Programming Language :: Python :: 3.9
Classifier: Operating System :: OS Independent
Requires-Python: >=3.7
License-File: LICENSE
License-File: LICENSE_RUS
